LICENSE
README.md
weevils/__init__.py
weevils/client.py
weevils/exceptions.py
weevils/models.py
weevils-0.0.2a1.dist-info/LICENSE
weevils-0.0.2a1.dist-info/WHEEL
weevils-0.0.2a1.dist-info/METADATA
weevils-0.0.2a1.dist-info/RECORD
