Metadata-Version: 2.1
Name: weevils
Version: 0.0.2a1
Summary: 
Home-page: https://docs.weevils.io/api-client
License: GPLv3
Author: weevils.io
Author-email: code@weevils.io
Requires-Python: >=3.7,<4.0
Classifier: Development Status :: 2 - Pre-Alpha
Classifier: License :: OSI Approved :: GNU General Public License v3 or later (GPLv3+)
Classifier: License :: Other/Proprietary License
Classifier: Programming Language :: Python :: 3
Classifier: Programming Language :: Python :: 3.10
Classifier: Programming Language :: Python :: 3.7
Classifier: Programming Language :: Python :: 3.8
Classifier: Programming Language :: Python :: 3.9
Requires-Dist: requests (>=2.12,<3.0)
